AnkiIn/__init__.py
AnkiIn/config.py
AnkiIn/log.py
AnkiIn/model.py
AnkiIn/note.py
AnkiIn/notetype_loader.py
AnkiIn/helper/__init__.py
AnkiIn/helper/ankiConnectHelper.py
AnkiIn/helper/formatHelper.py
AnkiIn/helper/genankiHelper.py
AnkiIn/notetypes/Choices.py
AnkiIn/notetypes/Cloze.py
AnkiIn/notetypes/ListCloze.py
AnkiIn/notetypes/MQA.py
AnkiIn/notetypes/QA.py
AnkiIn/notetypes/TableCloze.py
AnkiIn/notetypes/__init__.py
AnkiIn/parser/__init__.py
AnkiIn/parser/markdown.py
AnkiIn-0.1.7.dist-info/LICENSE
AnkiIn-0.1.7.dist-info/METADATA
AnkiIn-0.1.7.dist-info/WHEEL
AnkiIn-0.1.7.dist-info/top_level.txt
AnkiIn-0.1.7.dist-info/RECORD
