Metadata-Version: 2.1
Name: AnkiIn
Version: 0.1.7
Summary: Import markdown to Anki
Home-page: https://github.com/clouder0/AnkiIn
Author: Clouder
Author-email: clouder0@outlook.com
License: UNKNOWN
Project-URL: Bug Tracker, https://github.com/Clouder0/AnkiIn/issues
Platform: UNKNOWN
Classifier: Programming Language :: Python :: 3
Classifier: License :: OSI Approved :: MIT License
Classifier: Operating System :: OS Independent
Requires-Python: >=3.6
License-File: LICENSE
Requires-Dist: genanki (==0.11.0)
Requires-Dist: markdown2 (==2.4.0)
Requires-Dist: requests
Requires-Dist: aiohttp
Requires-Dist: toml
